MANIFEST.in
setup.py
Webapp_Enhanced.egg-info/PKG-INFO
Webapp_Enhanced.egg-info/SOURCES.txt
Webapp_Enhanced.egg-info/dependency_links.txt
Webapp_Enhanced.egg-info/top_level.txt
src/we
src/static/.DS_Store
src/static/.gitignore
src/static/__init__.py
src/static/app.yaml
src/static/main.py
src/static/abstract/.DS_Store
src/static/abstract/coffee/script.coffee
src/static/abstract/haml/.DS_Store
src/static/abstract/haml/home/.DS_Store
src/static/abstract/haml/home/index.haml
src/static/abstract/haml/layouts/base.haml
src/static/abstract/haml/layouts/make_delete.haml
src/static/abstract/haml/layouts/make_put.haml
src/static/abstract/sass/style.scss
src/static/assets/.DS_Store
src/static/assets/css/.DS_Store
src/static/assets/js/.DS_Store
src/static/controllers/.DS_Store
src/static/controllers/__init__.py
src/static/controllers/__init__.pyc
src/static/controllers/core.py
src/static/controllers/core.pyc
src/static/controllers/home.py
src/static/controllers/home.pyc
src/static/lib/.DS_Store
src/static/lib/__init__.py
src/static/lib/__init__.pyc
src/static/lib/db.py
src/static/lib/db.pyc
src/static/lib/server.py
src/static/lib/server.pyc
src/static/lib/xml/__init__.py
src/static/lib/xml/__init__.pyc
src/static/lib/xml/dicttoxml.py
src/static/lib/xml/dicttoxml.pyc
src/static/models/.DS_Store
src/static/models/__init__.py
src/static/models/__init__.pyc
src/static/temp/.DS_Store
src/static/temp/ajax
src/static/temp/controller-model
src/static/temp/controller-view
src/static/temp/model
src/static/temp/template
src/static/temp/template-model-edit
src/static/temp/template-model-index
src/static/temp/template-model-show
src/static/views/.DS_Store
src/static/views/home/.DS_Store
src/static/views/layouts/.DS_Store
webapp_enhanced.egg-info/SOURCES.txt