Metadata-Version: 1.0
Name: webapp-enhanced
Version: 1.0.2
Summary: Enhanced library for Google App Engine
Home-page: https://github.com/djwatt5/webapp-enhanced
Author: Daniel Watson
Author-email: watsondaniel6@gmail.com
License: MIT
Platform: UNKNOWN
